word_forms/__init__.py
word_forms/adj_to_adv.txt
word_forms/constants.py
word_forms/en-verbs.txt
word_forms/lemmatizer.py
word_forms/word_forms.py
word_forms-2.1.0.dist-info/LICENSE
word_forms-2.1.0.dist-info/METADATA
word_forms-2.1.0.dist-info/WHEEL
word_forms-2.1.0.dist-info/top_level.txt
word_forms-2.1.0.dist-info/RECORD
