Metadata-Version: 2.1
Name: word-forms
Version: 2.1.0
Summary: Generate all possible forms of an English word.
Home-page: https://github.com/gutfeeling/word_forms
Author: Dibya Chakravorty
Author-email: dibyachakravorty@gmail.com
License: UNKNOWN
Platform: UNKNOWN
Classifier: Programming Language :: Python :: 3
Classifier: License :: OSI Approved :: MIT License
Classifier: Operating System :: OS Independent
Requires-Python: >=3.6
